<annotation verified="yes">
    <folder>Annotation</folder>
    <filename>07aaab79-71ee-4ea3-a9e6-640191183947___3e7fd381-0ae5-4421-8a70-279ee0ec1c61_1208484d1392541449-nissan-terrano-official-review-img_20140215_181708.jpg</filename>
    <path>vehicle-PascalVOC-export/Annotations/07aaab79-71ee-4ea3-a9e6-640191183947___3e7fd381-0ae5-4421-8a70-279ee0ec1c61_1208484d1392541449-nissan-terrano-official-review-img_20140215_181708.jpg</path>
    <source>
        <database>Unknown</database>
    </source>
    <size>
        <width>2448</width>
        <height>2448</height>
        <depth>3</depth>
    </size>
    <segmented>0</segmented>
    <object>
    <name>plate</name>
    <pose>Unspecified</pose>
    <truncated>0</truncated>
    <difficult>0</difficult>
    <bndbox>
        <xmin>1292.8068640757415</xmin>
        <ymin>1726.047499834481</ymin>
        <xmax>1840.494873046875</xmax>
        <ymax>1847.7560166181145</ymax>
    </bndbox>
</object><object>
    <name>car</name>
    <pose>Unspecified</pose>
    <truncated>0</truncated>
    <difficult>0</difficult>
    <bndbox>
        <xmin>95.08474576271186</xmin>
        <ymin>224.05424783997617</ymin>
        <xmax>2377.1186440677966</xmax>
        <ymax>2199.0508474576272</ymax>
    </bndbox>
</object>
</annotation>
